alldebrid/__init__.py
alldebrid/alldebrid.py
alldebrid.py-1.0.5.dist-info/METADATA
alldebrid.py-1.0.5.dist-info/WHEEL
alldebrid.py-1.0.5.dist-info/top_level.txt
alldebrid.py-1.0.5.dist-info/RECORD
