Metadata-Version: 2.1
Name: alldebrid.py
Version: 1.0.5
Summary: Wrapper for the alldebrid API.
Requires-Dist: Requests (==2.30.0)
